.gitignore
Makefile
pyproject.toml
optisolveapi/__init__.py
optisolveapi/solver_base.py
optisolveapi/vector.py
optisolveapi.egg-info/PKG-INFO
optisolveapi.egg-info/SOURCES.txt
optisolveapi.egg-info/dependency_links.txt
optisolveapi.egg-info/requires.txt
optisolveapi.egg-info/top_level.txt
optisolveapi/milp/__init__.py
optisolveapi/milp/base.py
optisolveapi/milp/external.py
optisolveapi/milp/gurobi.py
optisolveapi/milp/sage.py
optisolveapi/milp/scip.py
optisolveapi/milp/swiglpk.py
optisolveapi/milp/symbase.py
optisolveapi/sat/__init__.py
optisolveapi/sat/base.py
optisolveapi/sat/constraints.py
optisolveapi/sat/ext.py
optisolveapi/sat/funcs.py
optisolveapi/sat/pysat.py
optisolveapi/sat/simple.py
tests/pulptest.py
tests/test_milp.py
tests/test_sat.py
tests/test_sat_cardinality.py